{
  "mappings": [
    {
      "name": "Cyrillic",
      "pairs": [
        [
          "ах'",
          "äx"
        ],
        [
          "хя",
          "xä"
        ],
        [
          "акь'",
          "äqh"
        ],
        [
          "кья",
          "qhä"
        ],
        [
          "гӀ",
          "ß"
        ],
        [
          "гІ",
          "ß"
        ],
        [
          "апӀ'",
          "äph"
        ],
        [
          "апІ'",
          "äph"
        ],
        [
          "пӀя",
          "phä"
        ],
        [
          "пІя",
          "phä"
        ],
        [
          "ахъ'",
          "äq"
        ],
        [
          "хъя",
          "qä"
        ],
        [
          "акъ'",
          "äģ"
        ],
        [
          "къя",
          "ģä"
        ],
        [
          "агъ'",
          "äğ"
        ],
        [
          "гъя",
          "ğä"
        ],
        [
          "ахӀ",
          "äh"
        ],
        [
          "ахІ",
          "äh"
        ],
        [
          "хӀа",
          "hä"
        ],
        [
          "хІа",
          "hä"
        ],
        [
          "ав'",
          "äv"
        ],
        [
          "вя",
          "vä"
        ],
        [
          "аб'",
          "äb"
        ],
        [
          "бя",
          "bä"
        ],
        [
          "ая",
          "aja"
        ],
        [
          "ае",
          "aje"
        ],
        [
          "аю",
          "aju"
        ],
        [
          "тӀ",
          "th"
        ],
        [
          "тІ",
          "th"
        ],
        [
          "пӀ",
          "ph"
        ],
        [
          "пІ",
          "ph"
        ],
        [
          "цӀ",
          "ch"
        ],
        [
          "цІ",
          "ch"
        ],
        [
          "чӀ",
          "čh"
        ],
        [
          "чІ",
          "čh"
        ],
        [
          "хъ",
          "q"
        ],
        [
          "къ",
          "ģ"
        ],
        [
          "кь",
          "qh"
        ],
        [
          "уь",
          "ü"
        ],
        [
          "гъ",
          "ğ"
        ],
        [
          "гь",
          "h"
        ],
        [
          "хь",
          "xh"
        ],
        [
          "кӀ",
          "kh"
        ],
        [
          "кІ",
          "kh"
        ],
        [
          "Ӏ",
          "ß"
        ],
        [
          "І",
          "ß"
        ],
        [
          "е",
          "e"
        ],
        [
          "а",
          "a"
        ],
        [
          "з",
          "z"
        ],
        [
          "ш",
          "š"
        ],
        [
          "е",
          "je"
        ],
        [
          "р",
          "r"
        ],
        [
          "т",
          "t"
        ],
        [
          "й",
          "j"
        ],
        [
          "у",
          "u"
        ],
        [
          "и",
          "i"
        ],
        [
          "п",
          "p"
        ],
        [
          "с",
          "s"
        ],
        [
          "д",
          "d"
        ],
        [
          "ф",
          "f"
        ],
        [
          "г",
          "g"
        ],
        [
          "ж",
          "ž"
        ],
        [
          "к",
          "k"
        ],
        [
          "л",
          "l"
        ],
        [
          "м",
          "m"
        ],
        [
          "х",
          "x"
        ],
        [
          "ц",
          "c"
        ],
        [
          "ч",
          "č"
        ],
        [
          "б",
          "b"
        ],
        [
          "н",
          "n"
        ],
        [
          "в",
          "v"
        ],
        [
          "э",
          "e"
        ],
        [
          "ъ",
          "y"
        ]
      ]
    },
    {
      "name": "Latin",
      "pairs": []
    }
  ],
  "sample": "Адиная Іисайилди Учин бавна ччуччар, халкь ппара ай, гъяйчІвас хьунда гиваривас Іисайилди. Іисайис хабар акьуна пуная: – Ве бавна Ве ччуччар гъузуная раккахъ, Вун агвас ккандий. Іисайи пуная гиварис: Зе бавна ччуччар гьа тивар э, Аллагьдин гафунил йиркІв алийина, гидихъ хъучавяттар."
}
